oc_wrapper/__init__.py
oc_wrapper/api.py
oc_wrapper/policy.py
tests/__init__.py
tests/test_api.py
tests/test_policy.py
oc_wrapper-0.1.0.dev0.dist-info/LICENSE
oc_wrapper-0.1.0.dev0.dist-info/METADATA
oc_wrapper-0.1.0.dev0.dist-info/WHEEL
oc_wrapper-0.1.0.dev0.dist-info/top_level.txt
oc_wrapper-0.1.0.dev0.dist-info/RECORD
