Metadata-Version: 2.1
Name: oc-wrapper
Version: 0.1.0.dev0
Summary: Python wrapper for OpenShift CLI (oc) command line tool.
Home-page: https://github.com/davidlukac/oc_wrapper
Author: David Lukac
Author-email: david.lukac@gmail.com
License: UNKNOWN
Platform: UNKNOWN
Classifier: Programming Language :: Python :: 2
Classifier: License :: OSI Approved :: MIT License
Classifier: Operating System :: OS Independent
